sp_defesacivil_divadmin/__init__.py
sp_defesacivil_divadmin/my_paths.py
sp_defesacivil_divadmin/data/output/geo/sp_defesacivil.7z
sp_defesacivil_divadmin/data/output/geo/sp_defesacivil_popup.7z
sp_defesacivil_divadmin/data/output/tabs/tab_defesacivil.csv
sp_defesacivil_divadmin-0.0.3.dist-info/LICENSE
sp_defesacivil_divadmin-0.0.3.dist-info/METADATA
sp_defesacivil_divadmin-0.0.3.dist-info/WHEEL
sp_defesacivil_divadmin-0.0.3.dist-info/top_level.txt
sp_defesacivil_divadmin-0.0.3.dist-info/RECORD
