Metadata-Version: 2.1
Name: sp_defesacivil_divadmin
Version: 0.0.3
Summary: Divisão Administrativa da Defesa Civil
Home-page: https://github.com/open-geodata/sp_defesacivil_divadmin
Author: Michel Metran
Author-email: michelmetran@gmail.com
Keywords: python,dados espaciais,geoprocessamento
Classifier: Programming Language :: Python :: 3
Classifier: License :: OSI Approved :: MIT License
Classifier: Operating System :: OS Independent
Classifier: Natural Language :: Portuguese
Classifier: Intended Audience :: Developers
Requires-Python: >=3
License-File: LICENSE
